llamasearch_pdf/__init__.py
llamasearch_pdf/__main__.py
llamasearch_pdf/cli/__init__.py
llamasearch_pdf/cli/metadata.py
llamasearch_pdf/cli/ocr.py
llamasearch_pdf/cli/search.py
llamasearch_pdf/cli/text.py
llamasearch_pdf/core/__init__.py
llamasearch_pdf/core/metadata.py
llamasearch_pdf/core/processor.py
llamasearch_pdf/core/text.py
llamasearch_pdf/ocr/__init__.py
llamasearch_pdf/ocr/engines.py
llamasearch_pdf/ocr/processor.py
llamasearch_pdf/search/__init__.py
llamasearch_pdf/search/index.py
llamasearch_pdf/utils/__init__.py
llamasearch_pdf/utils/image_utils.py
llamasearch_pdf_llamasearch-0.1.0.dist-info/licenses/LICENSE
llamasearch_pdf_llamasearch-0.1.0.dist-info/METADATA
llamasearch_pdf_llamasearch-0.1.0.dist-info/WHEEL
llamasearch_pdf_llamasearch-0.1.0.dist-info/entry_points.txt
llamasearch_pdf_llamasearch-0.1.0.dist-info/top_level.txt
llamasearch_pdf_llamasearch-0.1.0.dist-info/RECORD
