Metadata-Version: 2.4
Name: llamasearch-pdf-llamasearch
Version: 0.1.0
Summary: A comprehensive PDF processing toolkit for document workflows
Home-page: https://llamasearch.ai
Author: LlamaSearch AI
Author-email: llamasearch-pdf-llamasearch <nikjois@llamasearch.ai>
License: MIT License
Project-URL: Homepage, https://github.com/llamasearch-ai/llamasearch-pdf
Project-URL: Documentation, https://llamasearch-pdf.readthedocs.io
Project-URL: Repository, https://github.com/llamasearch-ai/llamasearch-pdf.git
Project-URL: Issues, https://github.com/llamasearch-ai/llamasearch-pdf/issues
Project-URL: Changelog, https://github.com/llamasearch-ai/llamasearch-pdf/blob/main/CHANGELOG.md
Keywords: pdf,ocr,text-extraction,metadata,search,document-processing
Classifier: Development Status :: 4 - Beta
Classifier: Intended Audience :: Developers
Classifier: License :: OSI Approved :: MIT License
Classifier: Programming Language :: Python :: 3
Classifier: Programming Language :: Python :: 3.8
Classifier: Programming Language :: Python :: 3.9
Classifier: Programming Language :: Python :: 3.10
Classifier: Programming Language :: Python :: 3.11
Classifier: Topic :: Scientific/Engineering :: Artificial Intelligence
Classifier: Topic :: Text Processing :: Indexing
Classifier: Topic :: Office/Business
Classifier: Topic :: Multimedia :: Graphics :: Capture :: Scanners
Classifier: Topic :: Utilities
Requires-Python: >=3.8
License-File: LICENSE
Requires-Dist: pdfminer.six>=20201018
Requires-Dist: PyPDF2>=2.0.0
Requires-Dist: python-poppler>=0.3.0
Requires-Dist: pytesseract>=0.3.8
Requires-Dist: Pillow>=8.0.0
Requires-Dist: tqdm>=4.50.0
Requires-Dist: numpy>=1.20.0
Requires-Dist: scikit-learn>=1.0.0
Requires-Dist: nltk>=3.6.0
Requires-Dist: click>=8.0.0
Requires-Dist: rich>=10.0.0
Requires-Dist: pyyaml>=6.0
Provides-Extra: ocrmypdf
Requires-Dist: ocrmypdf>=13.0.0; extra == "ocrmypdf"
Provides-Extra: huggingface
Requires-Dist: transformers>=4.15.0; extra == "huggingface"
Requires-Dist: torch>=1.10.0; extra == "huggingface"
Provides-Extra: search
Requires-Dist: scikit-learn>=1.0.0; extra == "search"
Requires-Dist: nltk>=3.6.0; extra == "search"
Requires-Dist: scipy>=1.7.0; extra == "search"
Provides-Extra: dev
Requires-Dist: pytest>=6.0.0; extra == "dev"
Requires-Dist: pytest-cov>=2.12.0; extra == "dev"
Requires-Dist: black>=21.5b2; extra == "dev"
Requires-Dist: isort>=5.9.0; extra == "dev"
Requires-Dist: flake8>=3.9.0; extra == "dev"
Requires-Dist: mypy>=0.812; extra == "dev"
Requires-Dist: pre-commit>=2.13.0; extra == "dev"
Provides-Extra: docs
Requires-Dist: mkdocs>=1.3.0; extra == "docs"
Requires-Dist: mkdocs-material>=8.2.0; extra == "docs"
Requires-Dist: mkdocstrings[python]>=0.19.0; extra == "docs"
Requires-Dist: mkdocs-include-markdown-plugin>=3.6.0; extra == "docs"
Requires-Dist: markdown-include>=0.7.0; extra == "docs"
Provides-Extra: all
Requires-Dist: ocrmypdf>=13.0.0; extra == "all"
Requires-Dist: transformers>=4.15.0; extra == "all"
Requires-Dist: torch>=1.10.0; extra == "all"
Requires-Dist: scikit-learn>=1.0.0; extra == "all"
Requires-Dist: nltk>=3.6.0; extra == "all"
Requires-Dist: scipy>=1.7.0; extra == "all"
Dynamic: author
Dynamic: home-page
Dynamic: license-file
Dynamic: requires-python
